docassemble/__init__.py
docassemble/MATCTheme/__init__.py
docassemble/MATCTheme/data/questions/matc_theme.yml
docassemble/MATCTheme/data/questions/questions.yml
docassemble/MATCTheme/data/questions/visual.yml
docassemble/MATCTheme/data/sources/README.md
docassemble/MATCTheme/data/static/Mass-Trial-Court-Seal-final-color.png
docassemble/MATCTheme/data/static/README.md
docassemble/MATCTheme/data/static/bootstrap.css
docassemble/MATCTheme/data/static/menu.js
docassemble/MATCTheme/data/static/navigation.css
docassemble/MATCTheme/data/templates/README.md
docassemble_matctheme-1.0.7.dist-info/licenses/LICENSE
docassemble_matctheme-1.0.7.dist-info/METADATA
docassemble_matctheme-1.0.7.dist-info/WHEEL
docassemble_matctheme-1.0.7.dist-info/top_level.txt
docassemble_matctheme-1.0.7.dist-info/RECORD
