Metadata-Version: 2.4
Name: docassemble.MATCTheme
Version: 1.0.7
Summary: A Docassemble Bootstrap theme for the Massachusetts Trial Court
Home-page: https://github.com/SuffolkLITLab/docassemble-MATCTheme/
Author: Sam Glover
Author-email: sam.glover@suffolk.edu
License: The MIT License (MIT)
License-File: LICENSE
Dynamic: author
Dynamic: author-email
Dynamic: description
Dynamic: description-content-type
Dynamic: home-page
Dynamic: license
Dynamic: license-file
Dynamic: summary
